3Hz_10Hz_Fs62.5Hz.dat
COPYING
MANIFEST.in
README
mod_sin.dat
setup.py
swan
swan.egg-info/PKG-INFO
swan.egg-info/SOURCES.txt
swan.egg-info/dependency_links.txt
swan.egg-info/top_level.txt
swan_modules/__init__.py
swan_modules/pycwt.py
swan_modules/pydwt.py
swan_modules/rhythm_track.py
swan_modules/utils.py
swan_modules/gui/Rhythm_path.py
swan_modules/gui/__init__.py
swan_modules/gui/swan_gtk.py
swan_modules/gui/swancmap.py
swan_modules/gui/swangui.py
swan_modules/gui/glade/swan.glade