Metadata-Version: 2.1
Name: swan
Version: 0.7.3
Summary: Easy continuous wavelet analysis
Home-page: http://cell.biophys.msu.ru/static/swan
Author: Alexey Brazhe
Author-email: brazhe@gmail.com
License: GNU GPL
Platform: UNKNOWN
Classifier: Development Status :: 4 - Beta
Classifier: Environment :: X11 Applications :: GTK
Classifier: Intended Audience :: End Users/Desktop
Classifier: License :: OSI Approved :: GNU General Public License (GPL)
Classifier: Operating System :: POSIX :: Linux
Classifier: Programming Language :: Python
Classifier: Topic :: Scientific/Engineering
License-File: COPYING
